{
  "STD" : "syphillis, Alpine",
  "total" : 0
},
{
  "STD": "syphillis, Central San Diego",
  "total": 370
},
{
  "STD": "syphillis, Southeastern San Diego",
  "total": 35
},
{
  "STD": "syphillis, Spring Valley",
  "total": 0
},
{
  "STD": "syphillis, Escondido",
  "total": 0
},
{
  "STD": "syphillis, Poway",
  "total": 0
},
{
  "STD": "syphillis, Lemon Grove",
  "total": 0
},
{
  "STD": "syphillis, Miramar",
  "total": 0
},
{
  "STD": "syphillis, Oceanside",
  "total": 0
},
{
  "STD": "syphillis, Carlsbad",
  "total": 0
},
{
  "STD": "syphillis, Mountain Empire",
  "total": 0
},
{
  "STD": "syphillis, Fallbrook",
  "total": 0
},
{
  "STD": "syphillis, San Marcos",
  "total": 0
},
{
  "STD": "syphillis, North Coastal Region",
  "total": 36
},
{
  "STD": "syphillis, North Central Region",
  "total": 109
},
{
  "STD": "syphillis, Sweetwater",
  "total": 0
},
{
  "STD": "syphillis, Unknown",
  "total": 0
},
{
  "STD": "syphillis, East Region",
  "total": 52
},
{
  "STD": "syphillis, Kearny Mesa",
  "total": 53
},
{
  "STD": "syphillis, Peninsula",
  "total":
},
{
  "STD": "syphillis, Palomar‐Julian",
  "total": 0
},
{
  "STD": "syphillis, Lakeside",
  "total": 0
},
{
  "STD": "syphillis, Anza‐Borrego Springs",
  "total": 0
},
{
  "STD": "syphillis, La Mesa",
  "total": 0
},
{
  "STD": "syphillis, Coastal",
  "total": 0
},
{
  "STD": "syphillis, Mid‐City",
  "total": 0
},
{
  "STD": "syphillis, Santee",
  "total": 0
},
{
  "STD": "syphillis, North San Diego",
  "total": 0
},
{
  "STD": "syphillis, Jamul",
  "total": 0
},
{
  "STD": "syphillis, Harbison Crest/El Cajon",
  "total": 0
},
{
  "STD": "syphillis, Del Mar‐Mira Mesa",
  "total": 0
},
{
  "STD": "syphillis, South Region",
  "total": 85
},
{
  "STD": "syphillis, Valley Center",
  "total": 0
},
{
  "STD": "syphillis, National City",
  "total": 0
},
{
  "STD": "syphillis, El Cajon",
  "total": 0
},
{
  "STD": "syphillis, Pendleton",
  "total": 0
},
{
  "STD": "syphillis, South Bay",
  "total": 23
},
{
  "STD": "syphillis, Central Region",
  "total": 109
},
{
  "STD": "syphillis, Ramona",
  "total": 0
},
{
  "STD": "syphillis, Chula Vista",
  "total": 37
},
{
  "STD": "syphillis, Elliott‐Navajo",
  "total": 0
},
{
  "STD": "syphillis, Coronado",
  "total": 0
},
{
  "STD": "syphillis, Pauma",
  "total": 0
},
{
  "STD": "syphillis, North Inland Region",
  "total": 31
},
{
  "STD": "syphillis, San Dieguito",
  "total": 0
},
{
  "STD": "syphillis, Laguna‐Pine  Valley",
  "total": 0
},
{
  "STD": "syphillis, University",
  "total": 0
},
{
  "STD": "syphillis, Vista",
  "total": 0
},
